json_handler_caramajau/__init__.py
json_handler_caramajau/json_handler.py
json_handler_caramajau/py.typed
json_handler_caramajau-0.1.2.dist-info/METADATA
json_handler_caramajau-0.1.2.dist-info/WHEEL
json_handler_caramajau-0.1.2.dist-info/licenses/LICENSE
json_handler_caramajau-0.1.2.dist-info/RECORD
