Metadata-Version: 2.4
Name: json_handler_caramajau
Version: 0.1.2
Summary: Code to make it easier to read and write to a JSON file
Project-URL: Homepage, https://github.com/Caramajau/json-handler
Project-URL: Issues, https://github.com/Caramajau/json-handler/issues
Author: Caramajau
License-Expression: MIT
License-File: LICENSE
Classifier: Intended Audience :: Developers
Classifier: License :: OSI Approved :: MIT License
Classifier: Natural Language :: English
Classifier: Operating System :: OS Independent
Classifier: Programming Language :: Python :: 3
Classifier: Programming Language :: Python :: 3.12
Classifier: Topic :: File Formats :: JSON
Classifier: Topic :: Software Development :: Libraries
Requires-Python: >=3.12
